eprempy/__init__.py
eprempy/__main__.py
eprempy/_project_main.py
eprempy/aliased.py
eprempy/atomic.py
eprempy/base/__init__.py
eprempy/base/_abcs.py
eprempy/base/_protocols.py
eprempy/base/_types.py
eprempy/base/abc.py
eprempy/base/mixins.py
eprempy/cli.py
eprempy/container.py
eprempy/datafile/__init__.py
eprempy/datafile/_core.py
eprempy/datafile/_interfaces.py
eprempy/datafile/_reference.py
eprempy/datafile/_viewers.py
eprempy/eprem.py
eprempy/etc.py
eprempy/exceptions.py
eprempy/interfaces.py
eprempy/measurable/__init__.py
eprempy/measured/__init__.py
eprempy/measured/_context.py
eprempy/measured/_convert.py
eprempy/measured/_factories.py
eprempy/measured/_object.py
eprempy/measured/_operators.py
eprempy/measured/_sequence.py
eprempy/measured/_types.py
eprempy/measured/_units.py
eprempy/measured/_value.py
eprempy/metric/__init__.py
eprempy/metric/_conversions.py
eprempy/metric/_defined.py
eprempy/metric/_dimensions.py
eprempy/metric/_exceptions.py
eprempy/metric/_reference.py
eprempy/metric/_systems.py
eprempy/metric/_types.py
eprempy/metric/_units.py
eprempy/numeric/__init__.py
eprempy/numeric/_array.py
eprempy/numeric/_data.py
eprempy/numeric/_factory.py
eprempy/numeric/_implementation.py
eprempy/numeric/_index.py
eprempy/numeric/_mixins.py
eprempy/numeric/_objects.py
eprempy/numeric/_operations.py
eprempy/numeric/_operators.py
eprempy/observable/__init__.py
eprempy/observable/_interfaces.py
eprempy/observable/_objects.py
eprempy/parameter/__init__.py
eprempy/parameter/_config.py
eprempy/parameter/_metadata.py
eprempy/parameter/_runtime.py
eprempy/parameter/_src.py
eprempy/parameter/reference.json
eprempy/parameter/reference.py
eprempy/parameter/sources.log
eprempy/paths.py
eprempy/physical/__init__.py
eprempy/physical/_array.py
eprempy/physical/_axes.py
eprempy/physical/_axis.py
eprempy/physical/_axis_factories.py
eprempy/physical/_exceptions.py
eprempy/physical/_object.py
eprempy/physical/_object_factories.py
eprempy/physical/_operations.py
eprempy-0.11.0.dist-info/LICENSE
eprempy-0.11.0.dist-info/METADATA
eprempy-0.11.0.dist-info/WHEEL
eprempy-0.11.0.dist-info/RECORD
