Metadata-Version: 2.1
Name: eprempy
Version: 0.11.0
Summary: Tools for working with EPREM simulation runs
License: BSD 3-Clause
Author: Matt Young
Requires-Python: >=3.9,<3.13
Classifier: License :: Other/Proprietary License
Classifier: Programming Language :: Python :: 3
Classifier: Programming Language :: Python :: 3.9
Classifier: Programming Language :: Python :: 3.10
Classifier: Programming Language :: Python :: 3.11
Classifier: Programming Language :: Python :: 3.12
Requires-Dist: matplotlib (>=3.6.0)
Requires-Dist: netCDF4 (>=1.5.8)
Requires-Dist: numpy (>=1.26.0,<2.0)
Requires-Dist: scipy (>=1.7.3)
Requires-Dist: typing-extensions (>=4.8.0,<5.0.0)
